simpleaml/__init__.py
Simpleaml-0.0.1.dist-info/METADATA
Simpleaml-0.0.1.dist-info/WHEEL
Simpleaml-0.0.1.dist-info/top_level.txt
Simpleaml-0.0.1.dist-info/RECORD
