Metadata-Version: 2.1
Name: Simpleaml
Version: 0.0.1
Summary: Library to make easier using Azure Machine Learning components. Simplify training and deployment process by exposing just necessary methods.
Home-page: http://packages.python.org/simpleaml
Author: Jose Luis Rosado
Author-email: jlopez.uc3@gmail.com
License: BSD
Keywords: Azure Machine Learning Library
Platform: UNKNOWN
Classifier: Development Status :: 3 - Alpha
Classifier: Topic :: Utilities
Classifier: License :: OSI Approved :: BSD License
Requires-Dist: setuptools (>=38.4.0)
